D_latch.v
module d_latch(
    input clk,rst_n,
    input d,
    output reg q,
    output q_bar
);

    always@(clk)
        begin
            if(!rst_n)
                q <= 0;
            else
                if(clk)
                    q <= d;
        end
    assign q_bar = ~q;
endmodule

D_latch_tb.v

module d_latch_tb;
    reg clk, rst_n, d;
    wire q,q_bar;

    d_latch dut(.clk(clk), .d(d), .rst_n(rst_n), .q(q), .q_bar(q_bar));

    initial
        begin
            clk = 0;
            d = 0;
            forever #5 clk = ~clk;
        end

    initial
        begin
            $monitor("At time: %0t, clk = %b, rst_n = %b, d = %b, q = %b, q_bar = %b", $time, clk, rst_n, d, q, q_bar);
            $dumpfile("D_latch.vcd");
            $dumpvars(0,dut);
            rst_n = 0;
            #10;
            rst_n = 1;
             #10 d = 0;
             #10 d = 1;
             #10 d = 1;
             #10 d = 0;
             #10 d = 1;
             #10;
             rst_n = 0;
        end
    initial
        begin
          #100 $finish;
        end

endmodule

D_latch.vcd
$date
	Thu Sep 04 19:32:33 2025
$end
$version
	Icarus Verilog
$end
$timescale
	1s
$end
$scope module d_latch_tb $end
$scope module dut $end
$var wire 1 ! clk $end
$var wire 1 " d $end
$var wire 1 # q_bar $end
$var wire 1 $ rst_n $end
$var reg 1 % q $end
$upscope $end
$upscope $end
$enddefinitions $end
#0
$dumpvars
0%
0$
1#
0"
0!
$end
#5
1!
#10
0!
1$
#15
1!
#20
0!
#25
1!
#30
0!
1"
#35
0#
1%
1!
#40
0!
#45
1!
#50
0!
0"
#55
1#
0%
1!
#60
0!
1"
#65
0#
1%
1!
#70
1#
0%
0!
0$
