T_latch.v
module t_latch(
    input  clk, t, rst_n,
    output reg q,
    output q_bar
);

always @(clk or negedge rst_n) begin
    if (!rst_n)
        q <= 0;          // async reset
    else if (clk) begin  // latch transparent when clk=1
        if (t)
            q <= ~q;     // toggle
        // else implicit hold
    end
    // when clk=0, latch holds
end

assign q_bar = ~q;

endmodule

T_latch_tb.v
module t_latch_tb;
    reg clk, rst_n, t;
    wire q, q_bar;

    t_latch dut(.clk(clk), .rst_n(rst_n), .t(t), .q(q), .q_bar(q_bar));

    initial begin
        clk = 0;
        rst_n = 0;
        forever #5 clk = ~clk;
    end

    initial begin
        $monitor("At time = %0t, reset = %b, t = %b, q = %b, q_bar = %b", $time, rst_n, t, q, q_bar);
        #10 rst_n = 1;
        #10 t = 0;
        #10 t = 0;
        #10 t = 1;
        #10 t = 0;
        #10 t = 1;
        #10 t = 0;
        #10 t = 1;
        #10 t = 1;
        #10 t = 0;
        #10 t = 1;
        #10 rst_n = 0;
        #10 t = 0;
    end
    initial begin
        $dumpfile("t_latch_dump.vcd");
        $dumpvars(0,dut);
        #150 $finish;
    end
endmodule

t_latch_dump.vcd
$date
	Fri Sep 05 21:30:58 2025
$end
$version
	Icarus Verilog
$end
$timescale
	1s
$end
$scope module t_latch_tb $end
$scope module dut $end
$var wire 1 ! clk $end
$var wire 1 " q_bar $end
$var wire 1 # rst_n $end
$var wire 1 $ t $end
$var reg 1 % q $end
$upscope $end
$upscope $end
$enddefinitions $end
#0
$dumpvars
0%
x$
0#
1"
0!
$end
#5
1!
#10
0!
1#
#15
1!
#20
0!
0$
#25
1!
#30
0!
#35
1!
#40
0!
1$
#45
0"
1%
1!
#50
0!
0$
#55
1!
#60
0!
1$
#65
1"
0%
1!
#70
0!
0$
#75
1!
#80
0!
1$
#85
0"
1%
1!
#90
0!
#95
1"
0%
1!
#100
0!
0$
#105
1!
#110
0!
1$
#115
0"
1%
1!
#120
1"
0%
0!
0#
#125
1!
#130
0!
0$
